keepasshttp/__init__.py
keepasshttp/__main__.py
keepasshttp/aes_256_cbc.py
keepasshttp/keepass_http.py
keepasshttp-1.4.1.dist-info/LICENSE.txt
keepasshttp-1.4.1.dist-info/METADATA
keepasshttp-1.4.1.dist-info/WHEEL
keepasshttp-1.4.1.dist-info/top_level.txt
keepasshttp-1.4.1.dist-info/RECORD
