Metadata-Version: 2.1
Name: keepasshttp
Version: 1.4.1
Summary: Python client for KeePassHTTP to interact with KeePass's credentials
Home-page: https://github.com/cyrbil/python_keepass_http
Author: Cyril DEMINGEON
Author-email: 1126098+cyrbil@users.noreply.github.com
License: License :: OSI Approved :: MIT License
Platform: UNKNOWN
Classifier: Development Status :: 5 - Production/Stable
Classifier: Intended Audience :: Developers
Classifier: License :: OSI Approved :: MIT License
Classifier: Programming Language :: Python
Classifier: Programming Language :: Python :: 2.6
Classifier: Programming Language :: Python :: 2.7
Classifier: Programming Language :: Python :: 3
Classifier: Programming Language :: Python :: 3.4
Classifier: Programming Language :: Python :: 3.5
Classifier: Programming Language :: Python :: 3.6
Classifier: Programming Language :: Python :: 3.7
Classifier: Programming Language :: Python :: 3.8
Classifier: Programming Language :: Python :: Implementation :: CPython
Classifier: Programming Language :: Python :: Implementation :: PyPy
Classifier: Topic :: Security
Requires-Dist: pycryptodome (>=3.8.2)
Requires-Dist: requests (>=2.19.1)
Requires-Dist: six (>=1.12.0)
Requires-Dist: ordereddict (>=1.1)
